surreal_orm/__init__.py
surreal_orm/connection_manager.py
surreal_orm/constants.py
surreal_orm/enum.py
surreal_orm/model_base.py
surreal_orm/py.typed
surreal_orm/query_set.py
surreal_orm/utils.py
surrealdb_orm-0.1.4.dist-info/METADATA
surrealdb_orm-0.1.4.dist-info/WHEEL
surrealdb_orm-0.1.4.dist-info/licenses/LICENSE
surrealdb_orm-0.1.4.dist-info/RECORD
