Metadata-Version: 2.4
Name: surrealdb-orm
Version: 0.1.4
Summary: SurrealDB ORM as 'DJango style' for Python with async support. Works with pydantic validation.
Project-URL: Homepage, https://github.com/EulogySnowfall/SurrealDB-ORM
Project-URL: Documentation, https://github.com/EulogySnowfall/SurrealDB-ORM
Project-URL: Repository, https://github.com/EulogySnowfall/SurrealDB-ORM.git
Project-URL: Issues, https://github.com/EulogySnowfall/SurrealDB-ORM/issues
Author-email: Yannick Croteau <yannick.croteau@gmail.com>
License: # MIT License
License-File: LICENSE
Classifier: Development Status :: 3 - Alpha
Classifier: License :: OSI Approved :: MIT License
Classifier: Operating System :: OS Independent
Classifier: Programming Language :: Python :: 3
Classifier: Programming Language :: Python :: 3.11
Classifier: Programming Language :: Python :: 3.12
Classifier: Programming Language :: Python :: 3.13
Classifier: Topic :: Database
Classifier: Topic :: Software Development :: Libraries :: Python Modules
Requires-Python: >=3.11
Requires-Dist: pydantic>=2.10.4
Requires-Dist: surrealdb>=0.4.1
